coopr.pyomo-3.6.4-py2.7-nspkg.pth
coopr/pyomo/__init__.py
coopr/pyomo/base/__init__.py
coopr/pyomo/base/block.py
coopr/pyomo/base/blockutil.py
coopr/pyomo/base/component.py
coopr/pyomo/base/component_order.py
coopr/pyomo/base/connector.py
coopr/pyomo/base/constraint.py
coopr/pyomo/base/DataPortal.py
coopr/pyomo/base/expr.py
coopr/pyomo/base/expression.py
coopr/pyomo/base/external.py
coopr/pyomo/base/instance2dat.py
coopr/pyomo/base/intrinsic_functions.py
coopr/pyomo/base/label.py
coopr/pyomo/base/log_config.py
coopr/pyomo/base/misc.py
coopr/pyomo/base/numvalue.py
coopr/pyomo/base/objective.py
coopr/pyomo/base/param.py
coopr/pyomo/base/piecewise.py
coopr/pyomo/base/plugin.py
coopr/pyomo/base/pyomo.py
coopr/pyomo/base/PyomoModel.py
coopr/pyomo/base/PyomoModelData.py
coopr/pyomo/base/rangeset.py
coopr/pyomo/base/set_types.py
coopr/pyomo/base/sets.py
coopr/pyomo/base/sos.py
coopr/pyomo/base/sparse_indexed_component.py
coopr/pyomo/base/suffix.py
coopr/pyomo/base/symbol_map.py
coopr/pyomo/base/util.py
coopr/pyomo/base/var.py
coopr/pyomo/check/__init__.py
coopr/pyomo/check/checker.py
coopr/pyomo/check/driver.py
coopr/pyomo/check/hooks.py
coopr/pyomo/check/runner.py
coopr/pyomo/check/script.py
coopr/pyomo/components/__init__.py
coopr/pyomo/components/action.py
coopr/pyomo/components/check.py
coopr/pyomo/data/__init__.py
coopr/pyomo/data/parse_datacmds.py
coopr/pyomo/data/process_data.py
coopr/pyomo/data/TableData.py
coopr/pyomo/expr/__init__.py
coopr/pyomo/expr/ampl_repn.py
coopr/pyomo/expr/canonical_repn.py
coopr/pyomo/expr/linear_repn.py
coopr/pyomo/plugins/__init__.py
coopr/pyomo/plugins/check/__init__.py
coopr/pyomo/plugins/check/checker.py
coopr/pyomo/plugins/check/function.py
coopr/pyomo/plugins/check/model.py
coopr/pyomo/plugins/check/checkers/__init__.py
coopr/pyomo/plugins/check/checkers/py3k/__init__.py
coopr/pyomo/plugins/check/checkers/py3k/printing.py
coopr/pyomo/plugins/check/checkers/py3k/range.py
coopr.pyomo-3.6.4.dist-info/DESCRIPTION.rst
coopr.pyomo-3.6.4.dist-info/entry_points.txt
coopr.pyomo-3.6.4.dist-info/METADATA
coopr.pyomo-3.6.4.dist-info/metadata.json
coopr.pyomo-3.6.4.dist-info/namespace_packages.txt
coopr.pyomo-3.6.4.dist-info/RECORD
coopr.pyomo-3.6.4.dist-info/top_level.txt
coopr.pyomo-3.6.4.dist-info/WHEEL
